{
  "tools.bookmark.setToCurrentPage": {
    "en": "Set to current page",
    "zh": "设为当前页"
  },
  "tools.watermark.optionsTitle": {
    "en": "Watermark Options",
    "zh": "水印选项"
  },
  "tools.watermark.textWatermark": {
    "en": "Text Watermark",
    "zh": "文字水印"
  },
  "tools.watermark.imageWatermark": {
    "en": "Image Watermark",
    "zh": "图片水印"
  },
  "tools.watermark.watermarkImage": {
    "en": "Watermark Image (PNG/JPG)",
    "zh": "水印图片 (PNG/JPG)"
  },
  "tools.watermark.enterText": {
    "en": "Please enter text for the watermark.",
    "zh": "请输入水印文字。"
  },
  "tools.watermark.selectImage": {
    "en": "Please select an image file for the watermark.",
    "zh": "请选择水印图片。"
  },
  "tools.watermark.unsupportedImage": {
    "en": "Unsupported image format. Please use PNG or JPG.",
    "zh": "不支持的图片格式，请使用 PNG 或 JPG。"
  },
  "tools.watermark.failed": {
    "en": "Failed to add watermark.",
    "zh": "添加水印失败。"
  },
  "tools.watermark.addButton": {
    "en": "Add Watermark",
    "zh": "添加水印"
  },
  "tools.watermark.successMessage": {
    "en": "Watermark added successfully!",
    "zh": "水印添加成功！"
  },
  "tools.headerFooter.headerTitle": {
    "en": "Header",
    "zh": "页眉"
  },
  "tools.headerFooter.footerTitle": {
    "en": "Footer",
    "zh": "页脚"
  },
  "tools.headerFooter.previewHint": {
    "en": "Enter header or footer text to see preview",
    "zh": "输入页眉或页脚文本以查看预览"
  },
  "tools.headerFooter.addButton": {
    "en": "Add Header & Footer",
    "zh": "添加页眉页脚"
  },
  "tools.headerFooter.successMessage": {
    "en": "Header & footer added successfully!",
    "zh": "页眉页脚添加成功！"
  },
  "tools.invertColors.invertButton": {
    "en": "Invert Colors",
    "zh": "反转颜色"
  },
  "tools.invertColors.successMessage": {
    "en": "Colors inverted successfully!",
    "zh": "颜色反转成功！"
  },
  "tools.backgroundColor.applyButton": {
    "en": "Apply Background",
    "zh": "应用背景"
  },
  "tools.backgroundColor.successMessage": {
    "en": "Background color applied successfully!",
    "zh": "背景颜色应用成功！"
  },
  "tools.textColor.modeLabel": {
    "en": "Text Type",
    "zh": "文本类型"
  },
  "tools.textColor.modeDark": {
    "en": "Dark text (light background)",
    "zh": "深色文字（浅色背景）"
  },
  "tools.textColor.modeLight": {
    "en": "Light text (dark background)",
    "zh": "浅色文字（深色背景）"
  },
  "tools.textColor.thresholdLabel": {
    "en": "Brightness Threshold",
    "zh": "亮度阈值"
  },
  "tools.textColor.thresholdHint": {
    "en": "Adjust to control which pixels are affected",
    "zh": "调整以控制哪些像素会被改变"
  },
  "tools.textColor.applyButton": {
    "en": "Apply Text Color",
    "zh": "应用文本颜色"
  },
  "tools.textColor.successMessage": {
    "en": "Text color applied successfully!",
    "zh": "文本颜色应用成功！"
  },
  "tools.stamps.instructionsTitle": {
    "en": "How to Add Stamps",
    "zh": "如何添加印章"
  },
  "tools.stamps.instruction1": {
    "en": "Click the Stamp tool (image icon) in the toolbar above",
    "zh": "点击上方工具栏中的印章工具（图片图标）"
  },
  "tools.stamps.instruction2": {
    "en": "Click \"Add image\" to upload your stamp image",
    "zh": "点击「添加图片」上传您的印章图片"
  },
  "tools.stamps.instruction3": {
    "en": "Click on the PDF where you want to place the stamp",
    "zh": "点击PDF中要放置印章的位置"
  },
  "tools.stamps.instruction4": {
    "en": "Drag to resize or reposition the stamp",
    "zh": "拖动以调整大小或重新定位印章"
  },
  "tools.stamps.instruction5": {
    "en": "Click \"Save Stamped PDF\" below when done",
    "zh": "完成后点击下方的「保存印章PDF」"
  },
  "tools.stamps.saveButton": {
    "en": "Save Stamped PDF",
    "zh": "保存印章PDF"
  },
  "tools.stamps.viewerNotReady": {
    "en": "Viewer not ready. Please wait for the PDF to load.",
    "zh": "查看器未就绪，请等待PDF加载完成。"
  },
  "tools.stamps.saveFailed": {
    "en": "Failed to save stamped PDF. Please try again.",
    "zh": "保存印章PDF失败，请重试。"
  },
  "tools.stamps.successMessage": {
    "en": "Stamps added successfully!",
    "zh": "印章添加成功！"
  },
  "tools.removeAnnotations.optionsTitle": {
    "en": "Removal Options",
    "zh": "删除选项"
  },
  "tools.removeAnnotations.successMessage": {
    "en": "Annotations removed successfully!",
    "zh": "注释删除成功！"
  },
  "tools.formFiller.uploadDescription": {
    "en": "Drag and drop a PDF form.",
    "zh": "拖放PDF表单到此处。"
  },
  "tools.formFiller.saveButton": {
    "en": "Save Form",
    "zh": "保存表单"
  },
  "tools.formFiller.successMessage": {
    "en": "Form saved successfully!",
    "zh": "表单保存成功！"
  },
  "tools.removeBlankPages.optionsTitle": {
    "en": "Detection Options",
    "zh": "检测选项"
  },
  "tools.removeBlankPages.successMessage": {
    "en": "Blank pages removed successfully!",
    "zh": "空白页移除成功！"
  },
  "tools.removeBlankPages.analyzingPages": {
    "en": "Reading pages and computing information entropy...",
    "zh": "正在读取页面并计算信息熵..."
  },
  "tools.removeBlankPages.sensitivity": {
    "en": "Sensitivity Threshold (0-100)",
    "zh": "灵敏度阈值 (0-100)"
  },
  "tools.removeBlankPages.sensitivityHint": {
    "en": "Higher sensitivity is more lenient, making pages with slight scanning noise/watermarks easily marked as blank. Recommended blank pages are greyed out with a red diagonal bar. Click cards directly to override: force keep or force delete.",
    "zh": "值越高判定条件越宽松，即使带有少许墨迹或噪点的页面也会被当成空白页删除。系统推荐删除的页面会显示为置灰和红圈禁止符。你可以直接点击卡片来强行保留或删除某页。"
  },
  "tools.removeBlankPages.autoBlank": {
    "en": "Detected Blank",
    "zh": "检测为空白"
  },
  "tools.removeBlankPages.manualKeep": {
    "en": "Forced Keep",
    "zh": "已强制保留"
  },
  "tools.removeBlankPages.manualRemove": {
    "en": "Forced Delete",
    "zh": "已标记删除"
  },
  "tools.removeBlankPages.entropy": {
    "en": "Entropy",
    "zh": "信息熵"
  },
  "tools.removeBlankPages.noBlankPages": {
    "en": "No blank pages found.",
    "zh": "未发现空白页。"
  },
  "tools.tableOfContents.optionsTitle": {
    "en": "TOC Options",
    "zh": "目录选项"
  },
  "tools.tableOfContents.generateButton": {
    "en": "Generate TOC",
    "zh": "生成目录"
  },
  "tools.tableOfContents.successMessage": {
    "en": "Table of contents generated successfully!",
    "zh": "目录生成成功！"
  },
  "tools.tableOfContents.options": {
    "en": "TOC Options",
    "zh": "目录选项"
  },
  "tools.tableOfContents.tocTitle": {
    "en": "TOC Title",
    "zh": "目录标题"
  },
  "tools.tableOfContents.fontFamily": {
    "en": "Font Family",
    "zh": "字体"
  },
  "tools.tableOfContents.addBookmark": {
    "en": "Add TOC entry to bookmarks",
    "zh": "将目录添加到书签"
  },
  "tools.tableOfContents.bookmarkRequired": {
    "en": "This tool generates a clickable table of contents from existing PDF bookmarks. Please ensure your PDF has bookmarks before using this tool. You can add bookmarks using the Edit Bookmarks tool.",
    "zh": "此工具从现有PDF书签生成可点击的目录。请确保您的PDF已有书签。您可以使用「编辑书签」工具添加书签。"
  }
}